exonweb/__init__.py
exonweb/flask/__init__.py
exonweb/flask/server.py
exonweb/flask/view.py
exonweb/gunicorn/__init__.py
exonweb/gunicorn/extserver.py
exonweb-7.1.dist-info/LICENSE.txt
exonweb-7.1.dist-info/METADATA
exonweb-7.1.dist-info/WHEEL
exonweb-7.1.dist-info/top_level.txt
exonweb-7.1.dist-info/RECORD
