Metadata-Version: 2.1
Name: exonweb
Version: 7.1
Summary: Simple lightweight framework and utils for web applications.
Author-email: ExonLabs <info@exonlabs.net>
License: BSD 3-Clause License
Project-URL: Documentation, https://exonlabs.github.io/py-exonweb
Project-URL: Repository, https://github.com/exonlabs/py-exonweb
Classifier: Development Status :: 5 - Production/Stable
Classifier: Intended Audience :: Developers
Classifier: License :: OSI Approved :: BSD License
Classifier: Operating System :: OS Independent
Classifier: Programming Language :: Python
Classifier: Programming Language :: Python :: 3.9
Classifier: Programming Language :: Python :: 3.10
Classifier: Programming Language :: Python :: 3.11
Classifier: Programming Language :: Python :: 3.12
Classifier: Topic :: Software Development :: Libraries
Classifier: Topic :: Software Development :: Libraries :: Python Modules
Requires-Python: >=3.9
License-File: LICENSE.txt
Requires-Dist: flask <3.0,>=2.3
Requires-Dist: Jinja2 <4.0,>=3.1
Requires-Dist: gunicorn <24.0,>=23.0
Provides-Extra: dev
